MANIFEST.in
README.rst
buildout.cfg
develop.cfg
requirements.txt
setup.py
version.txt
bob/__init__.py
bob.db.avspoof.egg-info/PKG-INFO
bob.db.avspoof.egg-info/SOURCES.txt
bob.db.avspoof.egg-info/dependency_links.txt
bob.db.avspoof.egg-info/entry_points.txt
bob.db.avspoof.egg-info/not-zip-safe
bob.db.avspoof.egg-info/requires.txt
bob.db.avspoof.egg-info/top_level.txt
bob/db/__init__.py
bob/db/avspoof/__init__.py
bob/db/avspoof/checkfiles.py
bob/db/avspoof/create.py
bob/db/avspoof/driver.py
bob/db/avspoof/dumplist.py
bob/db/avspoof/models.py
bob/db/avspoof/query.py
bob/db/avspoof/test.py
doc/conf.py
doc/guide.rst
doc/index.rst
doc/py_api.rst